README.md
setup.py
hickory/__init__.py
hickory/cli.py
hickory/constants.py
hickory/every_launchd.py
hickory/every_systemd.py
hickory/format_status.py
hickory/launchd.py
hickory/systemd.py
hickory/utils.py
hickory.egg-info/PKG-INFO
hickory.egg-info/SOURCES.txt
hickory.egg-info/dependency_links.txt
hickory.egg-info/entry_points.txt
hickory.egg-info/top_level.txt