Metadata-Version: 2.1
Name: hickory
Version: 1.0.0
Summary: The command line tool for scheduling Python scripts
Home-page: https://github.com/maxhumber/hickory
Author: Max Humber
Author-email: max.humber@gmail.com
License: MIT
Keywords: schedule,scheduling,launchd,systemd
Platform: UNKNOWN
Classifier: Development Status :: 4 - Beta
Classifier: Intended Audience :: Developers
Classifier: Topic :: Office/Business :: Scheduling
Classifier: Topic :: Terminals
Classifier: Operating System :: MacOS
Classifier: Operating System :: POSIX :: Linux
Requires-Python: >=3.6
